yfiles_jupyter_graphs_for_neo4j/Yfiles_Neo4j_Graphs.py
yfiles_jupyter_graphs_for_neo4j/__init__.py
yfiles_jupyter_graphs_for_neo4j-1.7.0.dist-info/licenses/LICENSE.md
yfiles_jupyter_graphs_for_neo4j-1.7.0.dist-info/METADATA
yfiles_jupyter_graphs_for_neo4j-1.7.0.dist-info/WHEEL
yfiles_jupyter_graphs_for_neo4j-1.7.0.dist-info/top_level.txt
yfiles_jupyter_graphs_for_neo4j-1.7.0.dist-info/RECORD
