Metadata-Version: 2.4
Name: yfiles_jupyter_graphs_for_neo4j
Version: 1.7.0
Summary: A Neo4j graph visualization package that uses the yfiles-jupyter-graphs widget
Author-email: yWorks Support Team <yfileshtml@yworks.com>
License: MIT License
Project-URL: License, https://github.com/yWorks/yfiles-jupyter-graphs-for-neo4j/blob/main/LICENSE.md
Project-URL: Bug Tracker, https://github.com/yWorks/yfiles-jupyter-graphs-for-neo4j/issues
Project-URL: Documentation, https://github.com/yWorks/yfiles-jupyter-graphs-for-neo4j/
Project-URL: Repository, https://github.com/yWorks/yfiles-jupyter-graphs-for-neo4j.git
Classifier: Development Status :: 5 - Production/Stable
Classifier: Framework :: IPython
Classifier: Intended Audience :: Developers
Classifier: Intended Audience :: Science/Research
Classifier: Programming Language :: Python :: 3
Classifier: Operating System :: OS Independent
Classifier: Framework :: Jupyter
Classifier: Framework :: Jupyter :: JupyterLab
Classifier: Framework :: Jupyter :: JupyterLab :: 3
Classifier: Framework :: Jupyter :: JupyterLab :: Extensions
Classifier: Framework :: Jupyter :: JupyterLab :: Extensions :: Prebuilt
Requires-Python: >=3.8
License-File: LICENSE.md
Requires-Dist: yfiles_jupyter_graphs>=1.10.0
Dynamic: license-file
